coders_utils/__init__.py
coders_utils/codecs.py
coders_utils/cyber_utils.py
coders_utils/date_utils.py
coders_utils/file_handlers.py
coders_utils/identifiers.py
coders_utils/regex_manager.py
coders_utils-0.0.2.dist-info/LICENSE
coders_utils-0.0.2.dist-info/METADATA
coders_utils-0.0.2.dist-info/WHEEL
coders_utils-0.0.2.dist-info/top_level.txt
coders_utils-0.0.2.dist-info/RECORD
